LICENSE.txt
setup.py
tinyaspect.py
tinyaspect.egg-info/PKG-INFO
tinyaspect.egg-info/SOURCES.txt
tinyaspect.egg-info/dependency_links.txt
tinyaspect.egg-info/requires.txt
tinyaspect.egg-info/top_level.txt