Metadata-Version: 1.0
Name: tinyaspect
Version: 0.2
Summary: Easy creation of decorators for methods and functions
Home-page: http://code.google.com/p/tinyaspect/
Author: Tristan Straub
Author-email: tristanstraub@gmail.com
License: UNKNOWN
Platform: UNKNOWN
